[
  {
    "video_id": "699",
    "duration": "long",
    "domain": "Film & Television",
    "sub_category": "Animation",
    "url": "https://www.youtube.com/watch?v=I2dv1jNM7gM",
    "videoID": "I2dv1jNM7gM",
    "question_id": "699-3",
    "task_type": "Action Recognition",
    "question": "What happens when the figures in the video are electrocuted?",
    "options": [
      "A. They become abnormal.",
      "B. They lose their memory.",
      "C. They become friendly.",
      "D. They yearn for a family."
    ],
    "answer": "B"
  }
]